html2pdf_chromium/__init__.py
html2pdf_chromium/converter.py
html2pdf_chromium-0.1.3.dist-info/licenses/LICENSE
html2pdf_chromium-0.1.3.dist-info/METADATA
html2pdf_chromium-0.1.3.dist-info/WHEEL
html2pdf_chromium-0.1.3.dist-info/top_level.txt
html2pdf_chromium-0.1.3.dist-info/RECORD
