Metadata-Version: 2.4
Name: html2pdf_chromium
Version: 0.1.3
Summary: Convert HTML to PDF using Chromium browsers with zero Python dependencies
Home-page: https://github.com/VBenevides/html2pdf_chromium
Author: Vinicius Benevides
Author-email: massaki1999@gmail.com
Classifier: Programming Language :: Python :: 3
Classifier: Operating System :: OS Independent
Classifier: License :: OSI Approved :: MIT License
Classifier: Intended Audience :: Developers
Classifier: Development Status :: 3 - Alpha
Requires-Python: >=3.7
License-File: LICENSE
Dynamic: author
Dynamic: author-email
Dynamic: classifier
Dynamic: description
Dynamic: description-content-type
Dynamic: home-page
Dynamic: license-file
Dynamic: requires-python
Dynamic: summary
